game/__init__.py
game/image/__init__.py
game/image/change.py
game/image/close.py
game/image/open.py
game/level/__init__.py
game/level/load.py
game/level/over.py
game/level/start.py
game/sound/__init__.py
game/sound/load.py
game/sound/pause.py
game/sound/play.py
mpl_talk-0.1.2.dist-info/WHEEL
mpl_talk-0.1.2.dist-info/METADATA
mpl_talk-0.1.2.dist-info/RECORD
